{
    "id": "121",
    "title": "Ders 108 - Hastalık ve Sağlık Kavramları 7",
    "year": 2026,
    "language": "tr",
    "description": "Hastalık ve Sağlık Kavramları ve okuma parçası",
    "hide_description": false,
    "poster": "https:\/\/i.voe.sx\/cache\/jli7c5ixpmiq_storyboard_L5.jpg",
    "backdrop": "https:\/\/i.voe.sx\/cache\/jli7c5ixpmiq_storyboard_L3.jpg",
    "poster_2": "https:\/\/pixibay.cc\/9hqwnnnmw83z.jpg",
    "backdrop_2": "https:\/\/pixibay.cc\/9hqwnnnmw83z_xt.jpg",
    "badges": {
        "featured": false,
        "recommended": false
    },
    "categories": [
        {
            "id": "3",
            "name": "Almanca A2",
            "category_image": "https:\/\/www.goethe.de\/resources\/files\/png168\/a2-formatkey-webp-w640r.png",
            "movie_count": 136
        }
    ],
    "actors": [
        {
            "id": "2",
            "name": "Almanca Öğretmeni",
            "actor_image": "https:\/\/www.yakamoztercume.com\/upload\/resim\/171.jpg",
            "movie_count": 237
        }
    ],
    "sources": [
        {
            "name": "Voe",
            "type": "voe",
            "url": "https:\/\/voe.sx\/jli7c5ixpmiq"
        },
        {
            "name": "Streamtape",
            "type": "streamtape",
            "url": "https:\/\/streamtape.com\/v\/8qdgOe728gHGkX\/Ders-108"
        },
        {
            "name": "Bysekoze",
            "type": "bysekoze",
            "url": "https:\/\/byse.sx\/5b9rovx4686c"
        },
        {
            "name": "EarnVids",
            "type": "earnvids",
            "url": "https:\/\/morencius.com\/file\/9hqwnnnmw83z"
        }
    ],
    "previous_movie_data": {
        "id": "120",
        "title": "Ders 107 - Hastalık ve Sağlık Kavramları 6",
        "poster": "https:\/\/i.voe.sx\/cache\/ivcl20sffmqg_storyboard_L5.jpg"
    },
    "next_movie_data": {
        "id": "122",
        "title": "Ders 109 - Hastalık ve Sağlık Kavramları 8",
        "poster": "https:\/\/i.voe.sx\/cache\/iyqk7ig7wfd2_storyboard_L5.jpg"
    },
    "subtitles": [],
    "last_updated": "2026-07-20T18:02:32+03:00"
}